scib_metrics/__init__.py
scib_metrics/_settings.py
scib_metrics/_types.py
scib_metrics/benchmark/__init__.py
scib_metrics/benchmark/_core.py
scib_metrics/metrics/__init__.py
scib_metrics/metrics/_graph_connectivity.py
scib_metrics/metrics/_isolated_labels.py
scib_metrics/metrics/_kbet.py
scib_metrics/metrics/_lisi.py
scib_metrics/metrics/_nmi_ari.py
scib_metrics/metrics/_pcr_comparison.py
scib_metrics/metrics/_silhouette.py
scib_metrics/nearest_neighbors/__init__.py
scib_metrics/nearest_neighbors/_dataclass.py
scib_metrics/nearest_neighbors/_jax.py
scib_metrics/nearest_neighbors/_pynndescent.py
scib_metrics/utils/__init__.py
scib_metrics/utils/_diffusion_nn.py
scib_metrics/utils/_dist.py
scib_metrics/utils/_kmeans.py
scib_metrics/utils/_lisi.py
scib_metrics/utils/_pca.py
scib_metrics/utils/_pcr.py
scib_metrics/utils/_silhouette.py
scib_metrics/utils/_utils.py
scib_metrics-0.5.7.dist-info/METADATA
scib_metrics-0.5.7.dist-info/WHEEL
scib_metrics-0.5.7.dist-info/licenses/LICENSE
scib_metrics-0.5.7.dist-info/RECORD
