Metadata-Version: 2.4
Name: scib-metrics
Version: 0.5.7
Summary: Accelerated and Python-only scIB metrics
Project-URL: Documentation, https://scib-metrics.readthedocs.io/
Project-URL: Source, https://github.com/yoseflab/scib-metrics
Project-URL: Home-page, https://github.com/yoseflab/scib-metrics
Author: Adam Gayoso
Maintainer-email: Adam Gayoso <adamgayoso@berkeley.edu>
License: BSD 3-Clause License
License-File: LICENSE
Requires-Python: >=3.11
Requires-Dist: anndata
Requires-Dist: chex
Requires-Dist: igraph>0.9.0
Requires-Dist: jax
Requires-Dist: jaxlib
Requires-Dist: matplotlib
Requires-Dist: numpy
Requires-Dist: pandas
Requires-Dist: plottable
Requires-Dist: pynndescent
Requires-Dist: rich
Requires-Dist: scanpy>=1.9
Requires-Dist: scikit-learn
Requires-Dist: scipy
Requires-Dist: tqdm
Requires-Dist: umap-learn>=0.5.0
Provides-Extra: dev
Requires-Dist: pre-commit; extra == 'dev'
Requires-Dist: twine>=4.0.2; extra == 'dev'
Provides-Extra: doc
Requires-Dist: ipykernel; extra == 'doc'
Requires-Dist: ipython; extra == 'doc'
Requires-Dist: myst-nb; extra == 'doc'
Requires-Dist: numba>=0.57.1; extra == 'doc'
Requires-Dist: scanpydoc[typehints]>=0.7.4; extra == 'doc'
Requires-Dist: sphinx-book-theme>=1.0; extra == 'doc'
Requires-Dist: sphinx-copybutton; extra == 'doc'
Requires-Dist: sphinx>=4; extra == 'doc'
Requires-Dist: sphinxcontrib-bibtex>=1.0.0; extra == 'doc'
Requires-Dist: sphinxext-opengraph; extra == 'doc'
Provides-Extra: parallel
Requires-Dist: joblib; extra == 'parallel'
Provides-Extra: test
Requires-Dist: black; extra == 'test'
Requires-Dist: coverage; extra == 'test'
Requires-Dist: flake8; extra == 'test'
Requires-Dist: harmonypy; extra == 'test'
Requires-Dist: joblib; extra == 'test'
Requires-Dist: numba>=0.57.1; extra == 'test'
Requires-Dist: pytest; extra == 'test'
Requires-Dist: scib>=1.1.4; extra == 'test'
Provides-Extra: tutorial
Requires-Dist: adjusttext; extra == 'tutorial'
Requires-Dist: goatools; extra == 'tutorial'
Requires-Dist: harmony-pytorch; extra == 'tutorial'
Requires-Dist: mygene; extra == 'tutorial'
Requires-Dist: numexpr; extra == 'tutorial'
Requires-Dist: plotnine; extra == 'tutorial'
Requires-Dist: pyliger; extra == 'tutorial'
Requires-Dist: rich; extra == 'tutorial'
Requires-Dist: scanorama; extra == 'tutorial'
Requires-Dist: scvi-tools; extra == 'tutorial'
